uaibot-1.2.7.dist-info/RECORD
uaibot-1.2.7.dist-info/WHEEL
uaibot-1.2.7.dist-info/top_level.txt
uaibot-1.2.7.dist-info/METADATA
uaibot-1.2.7.dist-info/licenses/LICENSE.md
uaibot/__init__.py
uaibot/py.typed
uaibot/uaibot_cpp_bind.cpython-311-darwin.so
uaibot/demo/_constrained_control_demo_1.py
uaibot/demo/_control_demo_1.py
uaibot/demo/__init__.py
uaibot/demo/demo.py
uaibot/tests/utils_test.py
uaibot/tests/test_o2o_smooth.py
uaibot/tests/test_control.py
uaibot/tests/test_diff_smooth.py
uaibot/tests/test_comparison_cpp_py.py
uaibot/tests/test_free_config.py
uaibot/tests/test_o2o.py
uaibot/simulation/simulation.py
uaibot/simulation/threejs_sim.js
uaibot/simulation/__init__.py
uaibot/utils/__init__.py
uaibot/utils/types.py
uaibot/utils/utils.py
uaibot/robot/_create_kinova_gen3.py
uaibot/robot/_create_darwin_mini_arm.py
uaibot/robot/_create_darwin_mini_leg_right.py
uaibot/robot/_constrained_control.py
uaibot/robot/_ikm.py
uaibot/robot/_compute_dist.py
uaibot/robot/_set_ani_frame.py
uaibot/robot/_check_free_config.py
uaibot/robot/_create_epson_t6.py
uaibot/robot/_create_kuka_lbr_iiwa.py
uaibot/robot/_create_jaco.py
uaibot/robot/_dyn_model.py
uaibot/robot/_create_davinci_arms.py
uaibot/robot/_create_staubli_tx60.py
uaibot/robot/_to_cpp.py
uaibot/robot/_dist_struct_robot_auto.py
uaibot/robot/_update_col_object.py
uaibot/robot/_jac_geo.py
uaibot/robot/__init__.py
uaibot/robot/_create_magician_e6.py
uaibot/robot/_gen_code.py
uaibot/robot/links.py
uaibot/robot/_create_ur_ur3e.py
uaibot/robot/_vector_field_rn.py
uaibot/robot/_create_kuka_kr5.py
uaibot/robot/_task_function.py
uaibot/robot/_jac_ana.py
uaibot/robot/_jac_jac_geo.py
uaibot/robot/_add_ani_frame.py
uaibot/robot/_create_davinci_chest.py
uaibot/robot/_vector_field_SE3.py
uaibot/robot/_create_abb_crb.py
uaibot/robot/_create_darwin_mini.py
uaibot/robot/_attach_object.py
uaibot/robot/robot.py
uaibot/robot/_fkm.py
uaibot/robot/_dist_struct_robot_obj.py
uaibot/robot/_detach_object.py
uaibot/robot/_create_davinci.py
uaibot/robot/_create_franka_emika_3.py
uaibot/robot/_add_col_object.py
uaibot/robot/_create_darwin_mini_leg_left.py
