Metadata-Version: 2.4
Name: uaibot
Version: 1.2.7
Summary: Uaibot, online robotic simulator
Author-email: Vinicius Goncalves et al <vinicius.marianog@gmail.com>
Project-URL: Homepage, https://uaibot.github.io/
Project-URL: Documentation, https://uaibot.github.io/docs/API_Reference/Python_API_reference/Python_API_reference.html
Project-URL: Repository, https://github.com/UAIbot/UAIbotPy
Project-URL: Issues, https://github.com/UAIbot/UAIbotPy/issues
Keywords: robotics,simulator
Classifier: Development Status :: 5 - Production/Stable
Classifier: Intended Audience :: Science/Research
Classifier: Intended Audience :: Education
Classifier: Topic :: Scientific/Engineering :: Artificial Intelligence
Classifier: Topic :: Software Development :: Libraries :: Python Modules
Classifier: Programming Language :: Python :: 3 :: Only
Classifier: Programming Language :: Python :: 3.10
Classifier: Programming Language :: Python :: 3.11
Classifier: Programming Language :: Python :: 3.12
Classifier: Programming Language :: Python :: 3.13
Classifier: Programming Language :: C++
Classifier: Operating System :: OS Independent
Classifier: Framework :: Jupyter
Classifier: Framework :: IPython
Requires-Python: >=3.10
License-File: LICENSE.md
Requires-Dist: colour>=0.1.5
Requires-Dist: httplib2>=0.20.4
Requires-Dist: ipython>=7.34
Requires-Dist: matplotlib>=3.10.0
Requires-Dist: numpy>=1.24
Requires-Dist: pybind11>=2.10
Requires-Dist: quadprog>=0.1.13
Requires-Dist: requests
Requires-Dist: scipy>=1.10
Provides-Extra: test
Requires-Dist: pytest; extra == "test"
Requires-Dist: nox; extra == "test"
Dynamic: license-file
